[
  {
    "model": "site_app.ParcelSize",
    "pk": 1,
    "fields": {
      "size": "SM"
    }
  },
  {
    "model": "site_app.ParcelSize",
    "pk": 2,
    "fields": {
      "size": "MD"
    }
  },
  {
    "model": "site_app.ParcelSize",
    "pk": 3,
    "fields": {
      "size": "XL"
    }
  },
  {
    "model": "site_app.PropertyType",
    "pk": 1,
    "fields": {
      "name": "ООО"
    }
  },
  {
    "model": "site_app.PropertyType",
    "pk": 2,
    "fields": {
      "name": "ИП"
    }
  },
  {
    "model": "site_app.PropertyType",
    "pk": 3,
    "fields": {
      "name": "ОАО"
    }
  },
  {
    "model": "site_app.PropertyType",
    "pk": 4,
    "fields": {
      "name": "ЗАО"
    }
  }
]
